genomap/__init__.py
genomap/genomap.py
genomap/bregman_genomap/__init__.py
genomap/bregman_genomap/bregman_genomap.py
genomap/genoAnnotate/__init__.py
genomap/genoAnnotate/genoAnnotate.py
genomap/genoClassification/__init__.py
genomap/genoClassification/genoClassification.py
genomap/genoDR/__init__.py
genomap/genoDR/genoDimReduction.py
genomap/genoMOI/__init__.py
genomap/genoMOI/genoMOI.py
genomap/genoNet/__init__.py
genomap/genoNet/genoNet.py
genomap/genoNetRegression/__init__.py
genomap/genoNetRegression/genoNet_regression.py
genomap/genoNetus/__init__.py
genomap/genoNetus/genoNetus.py
genomap/genoRegression/__init__.py
genomap/genoRegression/genoRegression.py
genomap/genoSig/__init__.py
genomap/genoSig/genoSig.py
genomap/genoTraj/__init__.py
genomap/genoTraj/genoTraj.py
genomap/genoVis/__init__.py
genomap/genoVis/genoVis.py
genomap/genomapOPT/__init__.py
genomap/genomapOPT/genomapOPT.py
genomap/genomapT/__init__.py
genomap/genomapT/genomapT.py
genomap/genotype/__init__.py
genomap/genotype/genotype.py
genomap/utils/ConvDEC.py
genomap/utils/ConvIDEC.py
genomap/utils/FcDEC.py
genomap/utils/FcIDEC.py
genomap/utils/__init__.py
genomap/utils/class_discriminative_opt.py
genomap/utils/gTraj_utils.py
genomap/utils/group_centroid_opt.py
genomap/utils/metrics.py
genomap/utils/util_Sig.py
genomap/utils/util_genoClassReg.py
genomap/utils/utils_MOI.py
genomap-1.3.6.dist-info/LICENSE.txt
genomap-1.3.6.dist-info/METADATA
genomap-1.3.6.dist-info/WHEEL
genomap-1.3.6.dist-info/top_level.txt
genomap-1.3.6.dist-info/RECORD
