Metadata-Version: 2.1
Name: genomap
Version: 1.3.6
Summary: Genomap converts tabular gene expression data into spatially meaningful images.
Home-page: https://github.com/xinglab-ai/genomap
Author: Md Tauhidul Islam
Author-email: tauhid@stanford.edu
Classifier: Programming Language :: Python :: 3
Classifier: Operating System :: OS Independent
Requires-Python: >=3.8
License-File: LICENSE.txt
Requires-Dist: anndata
Requires-Dist: bbknn
Requires-Dist: igraph
Requires-Dist: keras
Requires-Dist: leidenalg
Requires-Dist: lime
Requires-Dist: louvain
Requires-Dist: numpy
Requires-Dist: openpyxl
Requires-Dist: pandas
Requires-Dist: phate
Requires-Dist: pot
Requires-Dist: pybiomart
Requires-Dist: scanpy
Requires-Dist: scanorama
Requires-Dist: scipy
Requires-Dist: scikit-learn
Requires-Dist: tensorflow
Requires-Dist: torch
Requires-Dist: tqdm
Requires-Dist: umap-learn
